{
  "version": "6.0",
  "nxVersion": "20.8.4",
  "pathMappings": {},
  "nxJsonPlugins": [
    {
      "name": "@nx/js/typescript",
      "options": {
        "typecheck": {
          "targetName": "typecheck"
        },
        "build": {
          "targetName": "build",
          "configName": "tsconfig.lib.json",
          "buildDepsName": "build-deps",
          "watchDepsName": "watch-deps"
        }
      }
    }
  ],
  "fileMap": {
    "nonProjectFiles": [
      {
        "file": "nx.json",
        "hash": "5765339465868405630"
      },
      {
        "file": "package.json",
        "hash": "17793493831625804722"
      },
      {
        "file": ".nx/version-plans/version-plan-1768412151953.md",
        "hash": "2853316500885690478"
      },
      {
        "file": ".npmrc",
        "hash": "3244421341483603138"
      },
      {
        "file": ".github/workflows/ci.yaml",
        "hash": "2764094993101259470"
      },
      {
        "file": ".github/workflows/release-publish.yaml",
        "hash": "18335906264404291816"
      },
      {
        "file": ".yarnrc.yml",
        "hash": "2886304410880062839"
      },
      {
        "file": ".github/workflows/release.yaml",
        "hash": "17260329473418544146"
      },
      {
        "file": "yarn.lock",
        "hash": "605800910258890355"
      },
      {
        "file": ".gitignore",
        "hash": "8076772259331523985"
      },
      {
        "file": "turbo.json",
        "hash": "16402890210527540759"
      },
      {
        "file": "README.md",
        "hash": "602718546537743385"
      },
      {
        "file": ".yarn/install-state.gz",
        "hash": "17656495602940639554"
      }
    ],
    "projectFileMap": {
      "@repo/eslint-config": [
        {
          "file": "packages/eslint-config/README.md",
          "hash": "13754227653957484045"
        },
        {
          "file": "packages/eslint-config/base.js",
          "hash": "13415738514823582499",
          "deps": [
            "npm:@eslint/js",
            "npm:eslint-config-prettier",
            "npm:eslint-plugin-turbo",
            "npm:typescript-eslint@8.53.0",
            "npm:eslint-plugin-only-warn"
          ]
        },
        {
          "file": "packages/eslint-config/next.js",
          "hash": "14252493761496035585",
          "deps": [
            "npm:@eslint/js",
            "npm:eslint",
            "npm:eslint-config-prettier",
            "npm:typescript-eslint@8.53.0",
            "npm:eslint-plugin-react-hooks",
            "npm:eslint-plugin-react",
            "npm:globals",
            "npm:@next/eslint-plugin-next"
          ]
        },
        {
          "file": "packages/eslint-config/package.json",
          "hash": "15584607054065271924",
          "deps": [
            "npm:@eslint/js",
            "npm:@next/eslint-plugin-next",
            "npm:eslint",
            "npm:eslint-config-prettier",
            "npm:eslint-plugin-only-warn",
            "npm:eslint-plugin-react",
            "npm:eslint-plugin-react-hooks",
            "npm:eslint-plugin-turbo",
            "npm:globals",
            "npm:typescript@5.9.3",
            "npm:typescript-eslint@8.53.0"
          ]
        },
        {
          "file": "packages/eslint-config/react-internal.js",
          "hash": "3207875352665207252",
          "deps": [
            "npm:@eslint/js",
            "npm:eslint-config-prettier",
            "npm:typescript-eslint@8.53.0",
            "npm:eslint-plugin-react-hooks",
            "npm:eslint-plugin-react",
            "npm:globals"
          ]
        }
      ],
      "docs": [
        {
          "file": "apps/docs/.gitignore",
          "hash": "17053635035368931995"
        },
        {
          "file": "apps/docs/README.md",
          "hash": "1841608540073148912"
        },
        {
          "file": "apps/docs/app/favicon.ico",
          "hash": "9157999678830540297"
        },
        {
          "file": "apps/docs/app/fonts/GeistMonoVF.woff",
          "hash": "17799230542345324615"
        },
        {
          "file": "apps/docs/app/fonts/GeistVF.woff",
          "hash": "6578897518916770501"
        },
        {
          "file": "apps/docs/app/globals.css",
          "hash": "18293205821686026017"
        },
        {
          "file": "apps/docs/app/layout.tsx",
          "hash": "4529673636012425356",
          "deps": [
            "npm:next"
          ]
        },
        {
          "file": "apps/docs/app/page.module.css",
          "hash": "17272264164516448302"
        },
        {
          "file": "apps/docs/app/page.tsx",
          "hash": "10818913231982541219",
          "deps": [
            "npm:next"
          ]
        },
        {
          "file": "apps/docs/eslint.config.js",
          "hash": "2263959356359967658"
        },
        {
          "file": "apps/docs/next.config.js",
          "hash": "6567081978241091914"
        },
        {
          "file": "apps/docs/package.json",
          "hash": "10528975058187631716",
          "deps": [
            "@repo/eslint-config",
            "@repo/typescript-config",
            "npm:@types/node",
            "npm:@types/react",
            "npm:@types/react-dom",
            "npm:eslint",
            "npm:typescript",
            "@repo/ui",
            "npm:next",
            "npm:react",
            "npm:react-dom"
          ]
        },
        {
          "file": "apps/docs/public/file-text.svg",
          "hash": "17760084710797261418"
        },
        {
          "file": "apps/docs/public/globe.svg",
          "hash": "110250140041414884"
        },
        {
          "file": "apps/docs/public/next.svg",
          "hash": "8300767200008744458"
        },
        {
          "file": "apps/docs/public/turborepo-dark.svg",
          "hash": "5280435613635272558"
        },
        {
          "file": "apps/docs/public/turborepo-light.svg",
          "hash": "9618029098646958442"
        },
        {
          "file": "apps/docs/public/vercel.svg",
          "hash": "6508004213753618803"
        },
        {
          "file": "apps/docs/public/window.svg",
          "hash": "7242562813461725307"
        },
        {
          "file": "apps/docs/tsconfig.json",
          "hash": "15544717613430809260"
        }
      ],
      "@test-k/utils": [
        {
          "file": "packages/utils/CHANGELOG.md",
          "hash": "2165771034486578880"
        },
        {
          "file": "packages/utils/package.json",
          "hash": "6272325826681877765",
          "deps": [
            "npm:tsup",
            "npm:typescript@5.9.3"
          ]
        },
        {
          "file": "packages/utils/src/index.ts",
          "hash": "16645212785234869981"
        },
        {
          "file": "packages/utils/tsconfig.json",
          "hash": "775826979271608419"
        },
        {
          "file": "packages/utils/tsconfig.lib.json",
          "hash": "15803003697183376531"
        }
      ],
      "web": [
        {
          "file": "apps/web/.gitignore",
          "hash": "17053635035368931995"
        },
        {
          "file": "apps/web/README.md",
          "hash": "1841608540073148912"
        },
        {
          "file": "apps/web/app/favicon.ico",
          "hash": "9157999678830540297"
        },
        {
          "file": "apps/web/app/fonts/GeistMonoVF.woff",
          "hash": "17799230542345324615"
        },
        {
          "file": "apps/web/app/fonts/GeistVF.woff",
          "hash": "6578897518916770501"
        },
        {
          "file": "apps/web/app/globals.css",
          "hash": "18293205821686026017"
        },
        {
          "file": "apps/web/app/layout.tsx",
          "hash": "4529673636012425356",
          "deps": [
            "npm:next"
          ]
        },
        {
          "file": "apps/web/app/page.module.css",
          "hash": "17272264164516448302"
        },
        {
          "file": "apps/web/app/page.tsx",
          "hash": "5495571946631503401",
          "deps": [
            "npm:next"
          ]
        },
        {
          "file": "apps/web/eslint.config.js",
          "hash": "2263959356359967658"
        },
        {
          "file": "apps/web/next.config.js",
          "hash": "6567081978241091914"
        },
        {
          "file": "apps/web/package.json",
          "hash": "5649829043675848404",
          "deps": [
            "@repo/eslint-config",
            "@repo/typescript-config",
            "npm:@types/node",
            "npm:@types/react",
            "npm:@types/react-dom",
            "npm:eslint",
            "npm:typescript",
            "@repo/ui",
            "npm:next",
            "npm:react",
            "npm:react-dom"
          ]
        },
        {
          "file": "apps/web/public/file-text.svg",
          "hash": "17760084710797261418"
        },
        {
          "file": "apps/web/public/globe.svg",
          "hash": "110250140041414884"
        },
        {
          "file": "apps/web/public/next.svg",
          "hash": "8300767200008744458"
        },
        {
          "file": "apps/web/public/turborepo-dark.svg",
          "hash": "5280435613635272558"
        },
        {
          "file": "apps/web/public/turborepo-light.svg",
          "hash": "9618029098646958442"
        },
        {
          "file": "apps/web/public/vercel.svg",
          "hash": "6508004213753618803"
        },
        {
          "file": "apps/web/public/window.svg",
          "hash": "7242562813461725307"
        },
        {
          "file": "apps/web/tsconfig.json",
          "hash": "15544717613430809260"
        }
      ],
      "@repo/typescript-config": [
        {
          "file": "packages/typescript-config/base.json",
          "hash": "16582354637600534236"
        },
        {
          "file": "packages/typescript-config/nextjs.json",
          "hash": "5420817179880079656"
        },
        {
          "file": "packages/typescript-config/package.json",
          "hash": "471180667494266307"
        },
        {
          "file": "packages/typescript-config/react-library.json",
          "hash": "15305099616913920141"
        }
      ],
      "@test-k/core": [
        {
          "file": "packages/core/package.json",
          "hash": "17489789542065299647",
          "deps": [
            "npm:tsup",
            "npm:typescript@5.9.3"
          ]
        },
        {
          "file": "packages/core/src/index.ts",
          "hash": "9921210865718368831"
        },
        {
          "file": "packages/core/tsconfig.json",
          "hash": "775826979271608419"
        },
        {
          "file": "packages/core/tsconfig.lib.json",
          "hash": "15803003697183376531"
        }
      ],
      "@repo/ui": [
        {
          "file": "packages/ui/eslint.config.mjs",
          "hash": "5418178612699070611"
        },
        {
          "file": "packages/ui/package.json",
          "hash": "11427093995971714794",
          "deps": [
            "@repo/eslint-config",
            "@repo/typescript-config",
            "npm:@types/node",
            "npm:@types/react",
            "npm:@types/react-dom",
            "npm:eslint",
            "npm:typescript",
            "npm:react",
            "npm:react-dom"
          ]
        },
        {
          "file": "packages/ui/src/button.tsx",
          "hash": "2754452512218986212",
          "deps": [
            "npm:react"
          ]
        },
        {
          "file": "packages/ui/src/card.tsx",
          "hash": "10612423921115029066",
          "deps": [
            "npm:react"
          ]
        },
        {
          "file": "packages/ui/src/code.tsx",
          "hash": "12784955322640527990",
          "deps": [
            "npm:react"
          ]
        },
        {
          "file": "packages/ui/tsconfig.json",
          "hash": "701843663225452563"
        }
      ]
    }
  }
}